avikom_types/__init__.py
avikom_types/py.typed
avikom_types/version.py
avikom_types/avikom/__init__.py
avikom_types/avikom/assistance/__init__.py
avikom_types/avikom/assistance/assistance_level_pb2.py
avikom_types/avikom/assistance/assistance_level_pb2.pyi
avikom_types/avikom/assistance/assistance_level_pb2_grpc.py
avikom_types/avikom/assistance/choice_item_pb2.py
avikom_types/avikom/assistance/choice_item_pb2.pyi
avikom_types/avikom/assistance/choice_item_pb2_grpc.py
avikom_types/avikom/assistance/choices_config_pb2.py
avikom_types/avikom/assistance/choices_config_pb2.pyi
avikom_types/avikom/assistance/choices_config_pb2_grpc.py
avikom_types/avikom/assistance/instruction_media_pb2.py
avikom_types/avikom/assistance/instruction_media_pb2.pyi
avikom_types/avikom/assistance/instruction_media_pb2_grpc.py
avikom_types/avikom/assistance/instruction_media_value_pb2.py
avikom_types/avikom/assistance/instruction_media_value_pb2.pyi
avikom_types/avikom/assistance/instruction_media_value_pb2_grpc.py
avikom_types/avikom/assistance/instruction_meta_pb2.py
avikom_types/avikom/assistance/instruction_meta_pb2.pyi
avikom_types/avikom/assistance/instruction_meta_pb2_grpc.py
avikom_types/avikom/assistance/instruction_text_pb2.py
avikom_types/avikom/assistance/instruction_text_pb2.pyi
avikom_types/avikom/assistance/instruction_text_pb2_grpc.py
avikom_types/avikom/assistance/instruction_text_value_pb2.py
avikom_types/avikom/assistance/instruction_text_value_pb2.pyi
avikom_types/avikom/assistance/instruction_text_value_pb2_grpc.py
avikom_types/avikom/assistance/issue_pb2.py
avikom_types/avikom/assistance/issue_pb2.pyi
avikom_types/avikom/assistance/issue_pb2_grpc.py
avikom_types/avikom/assistance/issue_query_pb2.py
avikom_types/avikom/assistance/issue_query_pb2.pyi
avikom_types/avikom/assistance/issue_query_pb2_grpc.py
avikom_types/avikom/assistance/issue_service_pb2.py
avikom_types/avikom/assistance/issue_service_pb2.pyi
avikom_types/avikom/assistance/issue_service_pb2_grpc.py
avikom_types-0.10.10.dist-info/METADATA
avikom_types-0.10.10.dist-info/WHEEL
avikom_types-0.10.10.dist-info/top_level.txt
avikom_types-0.10.10.dist-info/RECORD
