Metadata-Version: 2.1
Name: avikom-types
Version: 0.10.10
Summary: Avikom Protocol Buffer Types
Home-page: https://gitlab.ub.uni-bielefeld.de/avikom/converter
Author: Alexander Neumann
Author-email: alneuman@techfak.uni-bielefeld.de
Keywords: avikom, protocol buffers
Classifier: Programming Language :: Python :: 3
Classifier: Development Status :: 4 - Beta
Requires-Dist: protobuf
Requires-Dist: grpcio
Requires-Dist: googleapis-common-protos
